Metadata-Version: 2.1
Name: Neuron-pypi-kaushalshah178
Version: 0.0.2
Summary: It is an implimentation of perceptron
Home-page: https://github.com/kaushalshah178/Neuron_pypi
Author: kaushalshah178
Author-email: kaushalshah178@gmail.com
License: UNKNOWN
Project-URL: Bug Tracker, https://github.com/kaushalshah178/Neuron_pypi/issues
Platform: UNKNOWN
Classifier: Programming Language :: Python :: 3
Classifier: License :: OSI Approved :: MIT License
Classifier: Operating System :: OS Independent
Requires-Python: >=3.7
License-File: LICENSE
Requires-Dist: numpy
Requires-Dist: tqdm
